{"code":"module.link('../common/namespace.js',{DDP:\"DDP\"},0);module.link('../common/livedata_connection');module.link('./client_convenience');\n\n// Initialize the default server connection and put it on Meteor.connection\n\n","map":{"version":3,"sources":["packages/ddp-client/client/client.js"],"sourcesContent":["export { DDP } from '../common/namespace.js';\n\nimport '../common/livedata_connection';\n\n// Initialize the default server connection and put it on Meteor.connection\nimport './client_convenience';\n"],"names":["DDP"],"mappings":"AAAA,SAASA,GAAG,QAAQ,yBAAyB;AAE7C,OAAO,gCAAgC;AAEvC,2EAA2E;AAC3E,OAAO,uBAAuB","file":"packages/ddp-client/client/client.js.map"},"sourceType":"module"}