{"code":"module.export({default:()=>AleaRandomGenerator});let RandomGenerator;module.link('./AbstractRandomGenerator',{default(v){RandomGenerator=v}},0);\n// Alea PRNG, which is not cryptographically strong\n// see http://baagoe.org/en/wiki/Better_random_numbers_for_javascript\n// for a full discussion and Alea implementation.\nfunction Alea(seeds) {\n    function Mash() {\n        let n = 0xefc8249d;\n        const mash = (data)=>{\n            data = data.toString();\n            for(let i = 0; i < data.length; i++){\n                n += data.charCodeAt(i);\n                let h = 0.02519603282416938 * n;\n                n = h >>> 0;\n                h -= n;\n                h *= n;\n                n = h >>> 0;\n                h -= n;\n                n += h * 0x100000000; // 2^32\n            }\n            return (n >>> 0) * 2.3283064365386963e-10; // 2^-32\n        };\n        mash.version = 'Mash 0.9';\n        return mash;\n    }\n    let s0 = 0;\n    let s1 = 0;\n    let s2 = 0;\n    let c = 1;\n    if (seeds.length === 0) {\n        seeds = [\n            +new Date\n        ];\n    }\n    let mash = Mash();\n    s0 = mash(' ');\n    s1 = mash(' ');\n    s2 = mash(' ');\n    for(let i = 0; i < seeds.length; i++){\n        s0 -= mash(seeds[i]);\n        if (s0 < 0) {\n            s0 += 1;\n        }\n        s1 -= mash(seeds[i]);\n        if (s1 < 0) {\n            s1 += 1;\n        }\n        s2 -= mash(seeds[i]);\n        if (s2 < 0) {\n            s2 += 1;\n        }\n    }\n    mash = null;\n    const random = ()=>{\n        const t = 2091639 * s0 + c * 2.3283064365386963e-10; // 2^-32\n        s0 = s1;\n        s1 = s2;\n        return s2 = t - (c = t | 0);\n    };\n    random.uint32 = ()=>random() * 0x100000000; // 2^32\n    random.fract53 = ()=>random() + (random() * 0x200000 | 0) * 1.1102230246251565e-16; // 2^-53\n    random.version = 'Alea 0.9';\n    random.args = seeds;\n    return random;\n}\nclass AleaRandomGenerator extends RandomGenerator {\n    /**\n   * @name Random.fraction\n   * @summary Return a number between 0 and 1, like `Math.random`.\n   * @locus Anywhere\n   */ fraction() {\n        return this.alea();\n    }\n    constructor({ seeds = [] } = {}){\n        super();\n        if (!seeds) {\n            throw new Error('No seeds were provided for Alea PRNG');\n        }\n        this.alea = Alea(seeds);\n    }\n}\n// options:\n// - seeds: an array\n//   whose items will be `toString`ed and used as the seed to the Alea\n//   algorithm\n\n","map":{"version":3,"sources":["packages/random/AleaRandomGenerator.js"],"sourcesContent":["import RandomGenerator from './AbstractRandomGenerator';\n\n// Alea PRNG, which is not cryptographically strong\n// see http://baagoe.org/en/wiki/Better_random_numbers_for_javascript\n// for a full discussion and Alea implementation.\nfunction Alea(seeds) {\n  function Mash() {\n    let n = 0xefc8249d;\n\n    const mash = (data) => {\n      data = data.toString();\n      for (let i = 0; i < data.length; i++) {\n        n += data.charCodeAt(i);\n        let h = 0.02519603282416938 * n;\n        n = h >>> 0;\n        h -= n;\n        h *= n;\n        n = h >>> 0;\n        h -= n;\n        n += h * 0x100000000; // 2^32\n      }\n      return (n >>> 0) * 2.3283064365386963e-10; // 2^-32\n    };\n\n    mash.version = 'Mash 0.9';\n    return mash;\n  }\n\n  let s0 = 0;\n  let s1 = 0;\n  let s2 = 0;\n  let c = 1;\n  if (seeds.length === 0) {\n    seeds = [+new Date];\n  }\n  let mash = Mash();\n  s0 = mash(' ');\n  s1 = mash(' ');\n  s2 = mash(' ');\n\n  for (let i = 0; i < seeds.length; i++) {\n    s0 -= mash(seeds[i]);\n    if (s0 < 0) {\n      s0 += 1;\n    }\n    s1 -= mash(seeds[i]);\n    if (s1 < 0) {\n      s1 += 1;\n    }\n    s2 -= mash(seeds[i]);\n    if (s2 < 0) {\n      s2 += 1;\n    }\n  }\n  mash = null;\n\n  const random = () => {\n    const t = (2091639 * s0) + (c * 2.3283064365386963e-10); // 2^-32\n    s0 = s1;\n    s1 = s2;\n    return s2 = t - (c = t | 0);\n  };\n\n  random.uint32 = () => random() * 0x100000000; // 2^32\n  random.fract53 = () => random() +\n        ((random() * 0x200000 | 0) * 1.1102230246251565e-16); // 2^-53\n\n  random.version = 'Alea 0.9';\n  random.args = seeds;\n  return random;\n}\n\n// options:\n// - seeds: an array\n//   whose items will be `toString`ed and used as the seed to the Alea\n//   algorithm\nexport default class AleaRandomGenerator extends RandomGenerator {\n  constructor ({ seeds = [] } = {}) {\n    super();\n    if (!seeds) {\n      throw new Error('No seeds were provided for Alea PRNG');\n    }\n    this.alea = Alea(seeds);\n  }\n\n  /**\n   * @name Random.fraction\n   * @summary Return a number between 0 and 1, like `Math.random`.\n   * @locus Anywhere\n   */\n  fraction () {\n    return this.alea();\n  }\n}\n"],"names":["RandomGenerator","Alea","seeds","Mash","n","mash","data","toString","i","length","charCodeAt","h","version","s0","s1","s2","c","Date","random","t","uint32","fract53","args","AleaRandomGenerator","fraction","alea","Error"],"mappings":"AAAA,OAAOA,qBAAqB,4BAA4B;AAExD,mDAAmD;AACnD,qEAAqE;AACrE,iDAAiD;AACjD,SAASC,KAAKC,KAAK;IACjB,SAASC;QACP,IAAIC,IAAI;QAER,MAAMC,OAAO,CAACC;YACZA,OAAOA,KAAKC,QAAQ;YACpB,IAAK,IAAIC,IAAI,GAAGA,IAAIF,KAAKG,MAAM,EAAED,IAAK;gBACpCJ,KAAKE,KAAKI,UAAU,CAACF;gBACrB,IAAIG,IAAI,sBAAsBP;gBAC9BA,IAAIO,MAAM;gBACVA,KAAKP;gBACLO,KAAKP;gBACLA,IAAIO,MAAM;gBACVA,KAAKP;gBACLA,KAAKO,IAAI,aAAa,OAAO;YAC/B;YACA,OAAO,AAACP,CAAAA,MAAM,CAAA,IAAK,wBAAwB,QAAQ;QACrD;QAEAC,KAAKO,OAAO,GAAG;QACf,OAAOP;IACT;IAEA,IAAIQ,KAAK;IACT,IAAIC,KAAK;IACT,IAAIC,KAAK;IACT,IAAIC,IAAI;IACR,IAAId,MAAMO,MAAM,KAAK,GAAG;QACtBP,QAAQ;YAAC,CAAC,IAAIe;SAAK;IACrB;IACA,IAAIZ,OAAOF;IACXU,KAAKR,KAAK;IACVS,KAAKT,KAAK;IACVU,KAAKV,KAAK;IAEV,IAAK,IAAIG,IAAI,GAAGA,IAAIN,MAAMO,MAAM,EAAED,IAAK;QACrCK,MAAMR,KAAKH,KAAK,CAACM,EAAE;QACnB,IAAIK,KAAK,GAAG;YACVA,MAAM;QACR;QACAC,MAAMT,KAAKH,KAAK,CAACM,EAAE;QACnB,IAAIM,KAAK,GAAG;YACVA,MAAM;QACR;QACAC,MAAMV,KAAKH,KAAK,CAACM,EAAE;QACnB,IAAIO,KAAK,GAAG;YACVA,MAAM;QACR;IACF;IACAV,OAAO;IAEP,MAAMa,SAAS;QACb,MAAMC,IAAI,AAAC,UAAUN,KAAOG,IAAI,wBAAyB,QAAQ;QACjEH,KAAKC;QACLA,KAAKC;QACL,OAAOA,KAAKI,IAAKH,CAAAA,IAAIG,IAAI,CAAA;IAC3B;IAEAD,OAAOE,MAAM,GAAG,IAAMF,WAAW,aAAa,OAAO;IACrDA,OAAOG,OAAO,GAAG,IAAMH,WAChB,AAACA,CAAAA,WAAW,WAAW,CAAA,IAAK,wBAAyB,QAAQ;IAEpEA,OAAON,OAAO,GAAG;IACjBM,OAAOI,IAAI,GAAGpB;IACd,OAAOgB;AACT;AAMe,MAAMK,4BAA4BvB;IAS/C;;;;GAIC,GACDwB,WAAY;QACV,OAAO,IAAI,CAACC,IAAI;IAClB;IAfA,YAAa,EAAEvB,QAAQ,EAAE,EAAE,GAAG,CAAC,CAAC,CAAE;QAChC,KAAK;QACL,IAAI,CAACA,OAAO;YACV,MAAM,IAAIwB,MAAM;QAClB;QACA,IAAI,CAACD,IAAI,GAAGxB,KAAKC;IACnB;AAUF;AArBA,WAAW;AACX,oBAAoB;AACpB,sEAAsE;AACtE,cAAc;AACd,SAAqBqB,iCAiBpB","file":"packages/random/AleaRandomGenerator.js.map"},"sourceType":"module"}